<?xml version = '1.0' encoding = 'UTF-8'?>
<!DOCTYPE properties SYSTEM "http://java.sun.com/dtd/properties.dtd">
<properties>
   <entry key="HCM_VACATION_TYPE.DATE_MODIFIED:db_column_not_null">false</entry>
   <entry key="HCM_VACATION_TYPE.VACATION_ARABIC:db_column_type">VARCHAR2</entry>
   <entry key="HCM_VACATION_TYPE.CREATED_BY:db_column_type">VARCHAR2</entry>
   <entry key="HCM_VACATION_TYPE.MODIFIED_BY:db_column_size">30</entry>
   <entry key="HCM_VACATION_TYPE:db_table_type">TABLE</entry>
   <entry key="HCM_VACATION_TYPE.DATE_MODIFIED:db_column_type">DATE</entry>
   <entry key="HCM_VACATION_TYPE.CODE:db_column_not_null">true</entry>
   <entry key="HCM_VACATION_TYPE.VACATION_FOREIGN:db_column_type">VARCHAR2</entry>
   <entry key="HCM_VACATION_TYPE.VACATION_ARABIC:db_column_size">80</entry>
   <entry key="return_single_result_set">false</entry>
   <entry key="HCM_VACATION_TYPE.VACATION_FOREIGN:db_column_not_null">false</entry>
   <entry key="HCM_VACATION_TYPE.MODIFIED_BY:db_column_not_null">false</entry>
   <entry key="HCM_VACATION_TYPE.CREATED_BY:db_column_size">30</entry>
   <entry key="HCM_VACATION_TYPE:db_column_6">DATE_MODIFIED</entry>
   <entry key="HCM_VACATION_TYPE.CREATED_BY:db_column_not_null">false</entry>
   <entry key="HCM_VACATION_TYPE:db_column_5">MODIFIED_BY</entry>
   <entry key="HCM_VACATION_TYPE:db_column_4">DATE_CREATED</entry>
   <entry key="root_descriptor_alias">HCM_VACATION_TYPE</entry>
   <entry key="HCM_VACATION_TYPE.CODE:db_column_type">NUMBER</entry>
   <entry key="HCM_VACATION_TYPE:db_column_3">CREATED_BY</entry>
   <entry key="HCM_VACATION_TYPE:db_column_2">VACATION_FOREIGN</entry>
   <entry key="HCM_VACATION_TYPE:db_column_1">VACATION_ARABIC</entry>
   <entry key="HCM_VACATION_TYPE:db_column_0">CODE</entry>
   <entry key="HCM_VACATION_TYPE.MODIFIED_BY:db_column_type">VARCHAR2</entry>
   <entry key="HCM_VACATION_TYPE.DATE_CREATED:db_column_not_null">false</entry>
   <entry key="HCM_VACATION_TYPE.CODE:db_column_scale">0</entry>
   <entry key="HCM_VACATION_TYPE.VACATION_FOREIGN:db_column_size">80</entry>
   <entry key="HCM_VACATION_TYPE.CODE:db_column_precision">3</entry>
   <entry key="HCM_VACATION_TYPE.DATE_CREATED:db_column_type">DATE</entry>
   <entry key="HCM_VACATION_TYPE.VACATION_ARABIC:db_column_not_null">false</entry>
</properties>