<?xml version="1.0" encoding="UTF-8" ?>
<!-- Generated by Oracle SOA Modeler version 12.2.1.1.0.160608 at [8/23/17 3:30 PM]. -->
<composite name="EmployeeProfileInquiry"
           revision="1.0"
           label="2017-08-23_15-30-12_900"
           mode="active"
           state="on"
           xmlns="http://xmlns.oracle.com/sca/1.0"
           xmlns:xs="http://www.w3.org/2001/XMLSchema"
           xmlns:wsp="http://schemas.xmlsoap.org/ws/2004/09/policy"
           xmlns:orawsp="http://schemas.oracle.com/ws/2006/01/policy"
           xmlns:ui="http://xmlns.oracle.com/soa/designer/"
           xmlns:sca-ext="http://xmlns.oracle.com/sca/1.0-ext">
  <import namespace="http://xmlns.oracle.com/pcbpel/adapter/db/CAM_INQUIRY/EmployeeProfileInquiry/HRDBReference"
          location="WSDLs/HRDBReference.wsdl" importType="wsdl"/>
  <import namespace="http://xmlns.oracle.com/CAM_INQUIRY/EmployeeProfileInquiry/EmployeeProfileInquiry"
          location="WSDLs/EmployeeProfileInquiry.wsdl" importType="wsdl"/>
  <service name="EmployeeProfileInquiryService_ep" ui:wsdlLocation="WSDLs/EmployeeProfileInquiry.wsdl">
    <interface.wsdl interface="http://xmlns.oracle.com/CAM_INQUIRY/EmployeeProfileInquiry/EmployeeProfileInquiry#wsdl.interface(EmployeeProfileInquiry)"/>
    <binding.ws port="http://xmlns.oracle.com/CAM_INQUIRY/EmployeeProfileInquiry/EmployeeProfileInquiry#wsdl.endpoint(EmployeeProfileInquiryService_ep/EmployeeProfileInquiry_pt)"/>
  </service>
  <property name="productVersion" type="xs:string" many="false">12.2.1.1.0.160608</property>
  <property name="compositeID" type="xs:string" many="false">5005fadb-5892-4dd5-8394-fac2bfd5d0ba</property>
  <component name="EmployeeProfileInquiry" version="2.0">
    <implementation.bpel src="BPEL/EmployeeProfileInquiry.bpel"/>
    <componentType>
      <service name="EmployeeProfileInquiryService" ui:wsdlLocation="WSDLs/EmployeeProfileInquiry.wsdl">
        <interface.wsdl interface="http://xmlns.oracle.com/CAM_INQUIRY/EmployeeProfileInquiry/EmployeeProfileInquiry#wsdl.interface(EmployeeProfileInquiry)"/>
      </service>
      <reference name="HRDBReference" ui:wsdlLocation="WSDLs/HRDBReference.wsdl">
        <interface.wsdl interface="http://xmlns.oracle.com/pcbpel/adapter/db/CAM_INQUIRY/EmployeeProfileInquiry/HRDBReference#wsdl.interface(HRDBReference_ptt)"/>
      </reference>
    </componentType>
    <property name="bpel.config.transaction" type="xs:string" many="false">notSupported</property>
  </component>
  <reference name="HRDBReference" ui:wsdlLocation="WSDLs/HRDBReference.wsdl">
    <interface.wsdl interface="http://xmlns.oracle.com/pcbpel/adapter/db/CAM_INQUIRY/EmployeeProfileInquiry/HRDBReference#wsdl.interface(HRDBReference_ptt)"/>
    <binding.jca config="Adapters/HRDBReference_db.jca"/>
    <property name="jca.retry.count" type="xs:int" many="false" override="may">4</property>
    <property name="jca.retry.interval" type="xs:int" many="false" override="may">1</property>
    <property name="jca.retry.backoff" type="xs:int" many="false" override="may">2</property>
    <property name="jca.retry.maxInterval" type="xs:int" many="false" override="may">120</property>
  </reference>
  <wire>
    <source.uri>EmployeeProfileInquiryService_ep</source.uri>
    <target.uri>EmployeeProfileInquiry/EmployeeProfileInquiryService</target.uri>
  </wire>
  <wire>
    <source.uri>EmployeeProfileInquiry/HRDBReference</source.uri>
    <target.uri>HRDBReference</target.uri>
  </wire>
</composite>
